Workbook

Sheet SIMULADOR
A1: SIMULADOR DE INVESTIMENTOS EM FIIs
A2: Projeção de patrimônio, rendimentos e distribuição de carteira em Fundos de Investimento Imobiliário
B4: 1 · DADOS DO INVESTIDOR | G4: 2 · RESULTADOS DA SIMULAÇÃO
B5: Salário mensal | D5: 5000 | G5: Total aportado no período | I5: =PATRIMONIO_INICIAL+APORTE*PRAZO_ANOS*12 -> 125000
B6: % da renda p/ investimentos | D6: 0.2 | G6: Patrimônio final projetado | I6: =FV(TAXA_MENSAL,PRAZO_ANOS*12,-APORTE,-PATRIMONIO_INICIAL,0) -> 213226.17
B7: Sugestão de aporte (calculada) | D7: =SALARIO*PERCENTUAL_INVESTIMENTO -> 1000 | G7: Total de rendimentos obtidos | I7: =I6-I5 -> 88226.168
B8: Aporte mensal (definido pelo usuário) | D8: 1000 | G8: Dividendos mensais estimados | I8: =I6*DY_MENSAL -> 1492.5832
B9: Patrimônio inicial | D9: 5000 | G9: Dividendos anuais estimados | I9: =I8*12 -> 17910.998
B10: Prazo do investimento (anos) | D10: 10 | G10: Perfil selecionado | I10: =PERFIL -> Moderado
B11: Taxa de rendimento mensal esperada | D11: 0.008 | G11: Rendimento sobre o aportado | I11: =I7/I5 -> 0.70580935
B12: Dividend Yield mensal estimado | D12: 0.007
B13: Perfil do investidor | D13: Moderado
B14: Aporte informado vs. sugerido | D14: =IF(APORTE>=D7,"Acima/igual à sugestão ✓","Abaixo da sugestão") -> Acima/igual à sugestão ✓
B16: 3 · CENÁRIOS POR PRAZO (usa o aporte e as taxas informadas acima)
B17: Prazo (anos) | D17: Total aportado | F17: Patrimônio projetado | H17: Rendimento acumulado | J17: Dividendos mensais
B18: 2 | D18: =PATRIMONIO_INICIAL+APORTE*B18*12 -> 29000 | F18: =FV(TAXA_MENSAL,B18*12,-APORTE,-PATRIMONIO_INICIAL,0) -> 32396.881 | H18: =F18-D18 -> 3396.8813 | J18: =F18*DY_MENSAL -> 226.77817
B19: 5 | D19: =PATRIMONIO_INICIAL+APORTE*B19*12 -> 65000 | F19: =FV(TAXA_MENSAL,B19*12,-APORTE,-PATRIMONIO_INICIAL,0) -> 84688.822 | H19: =F19-D19 -> 19688.822 | J19: =F19*DY_MENSAL -> 592.82175
B20: 10 | D20: =PATRIMONIO_INICIAL+APORTE*B20*12 -> 125000 | F20: =FV(TAXA_MENSAL,B20*12,-APORTE,-PATRIMONIO_INICIAL,0) -> 213226.17 | H20: =F20-D20 -> 88226.168 | J20: =F20*DY_MENSAL -> 1492.5832
B21: 20 | D21: =PATRIMONIO_INICIAL+APORTE*B21*12 -> 245000 | F21: =FV(TAXA_MENSAL,B21*12,-APORTE,-PATRIMONIO_INICIAL,0) -> 754976.47 | H21: =F21-D21 -> 509976.47 | J21: =F21*DY_MENSAL -> 5284.8353
B22: 30 | D22: =PATRIMONIO_INICIAL+APORTE*B22*12 -> 365000 | F22: =FV(TAXA_MENSAL,B22*12,-APORTE,-PATRIMONIO_INICIAL,0) -> 2164469.8 | H22: =F22-D22 -> 1799469.8 | J22: =F22*DY_MENSAL -> 15151.288
B24: 4 · SUGESTÃO DE CARTEIRA — distribuição por tipo de FII conforme o perfil selecionado
B25: Tipo de FII | D25: Percentual sugerido | F25: Valor mensal destinado
B26: Papel | D26: =INDEX(BASE_FII!$B$5:$G$7,MATCH(PERFIL,BASE_FII!$A$5:$A$7,0),MATCH(B26,BASE_FII!$B$4:$G$4,0)) -> 0.25 | F26: =D26*APORTE -> 250
B27: Tijolo | D27: =INDEX(BASE_FII!$B$5:$G$7,MATCH(PERFIL,BASE_FII!$A$5:$A$7,0),MATCH(B27,BASE_FII!$B$4:$G$4,0)) -> 0.25 | F27: =D27*APORTE -> 250
B28: Híbridos | D28: =INDEX(BASE_FII!$B$5:$G$7,MATCH(PERFIL,BASE_FII!$A$5:$A$7,0),MATCH(B28,BASE_FII!$B$4:$G$4,0)) -> 0.2 | F28: =D28*APORTE -> 200
B29: FOFs | D29: =INDEX(BASE_FII!$B$5:$G$7,MATCH(PERFIL,BASE_FII!$A$5:$A$7,0),MATCH(B29,BASE_FII!$B$4:$G$4,0)) -> 0.15 | F29: =D29*APORTE -> 150
B30: Desenvolvimento | D30: =INDEX(BASE_FII!$B$5:$G$7,MATCH(PERFIL,BASE_FII!$A$5:$A$7,0),MATCH(B30,BASE_FII!$B$4:$G$4,0)) -> 0.1 | F30: =D30*APORTE -> 100
B31: Hotelaria | D31: =INDEX(BASE_FII!$B$5:$G$7,MATCH(PERFIL,BASE_FII!$A$5:$A$7,0),MATCH(B31,BASE_FII!$B$4:$G$4,0)) -> 0.05 | F31: =D31*APORTE -> 50
B32: TOTAL | D32: =SUM(D26:D31) -> 1 | F32: =SUM(F26:F31) -> 1000
B34: 5 · VISUALIZAÇÃO GRÁFICA
B57: Células em amarelo = campos editáveis pelo usuário · Células em cinza = calculadas automaticamente pela planilha

Sheet PROJEÇÃO
A1: PROJEÇÃO MÊS A MÊS — EVOLUÇÃO DO PATRIMÔNIO (360 MESES / 30 ANOS)
A2: Mês | B2: Ano | C2: Saldo inicial | D2: Aporte | E2: Rendimento do mês | F2: Saldo final | G2: Dividendos estimados | H2: Total aportado (acum.)
A3: 1 | B3: =ROUNDUP(A3/12,0) -> 1 | C3: =PATRIMONIO_INICIAL -> 5000 | D3: =APORTE -> 1000 | E3: =C3*TAXA_MENSAL -> 40 | F3: =C3+D3+E3 -> 6040 | G3: =F3*DY_MENSAL -> 42.28 | H3: =PATRIMONIO_INICIAL+D3 -> 6000
A4: 2 | B4: =ROUNDUP(A4/12,0) -> 1 | C4: =F3 -> 6040 | D4: =APORTE -> 1000 | E4: =C4*TAXA_MENSAL -> 48.32 | F4: =C4+D4+E4 -> 7088.32 | G4: =F4*DY_MENSAL -> 49.61824 | H4: =H3+D4 -> 7000
A5: 3 | B5: =ROUNDUP(A5/12,0) -> 1 | C5: =F4 -> 7088.32 | D5: =APORTE -> 1000 | E5: =C5*TAXA_MENSAL -> 56.70656 | F5: =C5+D5+E5 -> 8145.0266 | G5: =F5*DY_MENSAL -> 57.015186 | H5: =H4+D5 -> 8000
A6: 4 | B6: =ROUNDUP(A6/12,0) -> 1 | C6: =F5 -> 8145.0266 | D6: =APORTE -> 1000 | E6: =C6*TAXA_MENSAL -> 65.160212 | F6: =C6+D6+E6 -> 9210.1868 | G6: =F6*DY_MENSAL -> 64.471307 | H6: =H5+D6 -> 9000
A7: 5 | B7: =ROUNDUP(A7/12,0) -> 1 | C7: =F6 -> 9210.1868 | D7: =APORTE -> 1000 | E7: =C7*TAXA_MENSAL -> 73.681494 | F7: =C7+D7+E7 -> 10283.868 | G7: =F7*DY_MENSAL -> 71.987078 | H7: =H6+D7 -> 10000
A8: 6 | B8: =ROUNDUP(A8/12,0) -> 1 | C8: =F7 -> 10283.868 | D8: =APORTE -> 1000 | E8: =C8*TAXA_MENSAL -> 82.270946 | F8: =C8+D8+E8 -> 11366.139 | G8: =F8*DY_MENSAL -> 79.562974 | H8: =H7+D8 -> 11000
A9: 7 | B9: =ROUNDUP(A9/12,0) -> 1 | C9: =F8 -> 11366.139 | D9: =APORTE -> 1000 | E9: =C9*TAXA_MENSAL -> 90.929114 | F9: =C9+D9+E9 -> 12457.068 | G9: =F9*DY_MENSAL -> 87.199478 | H9: =H8+D9 -> 12000
A10: 8 | B10: =ROUNDUP(A10/12,0) -> 1 | C10: =F9 -> 12457.068 | D10: =APORTE -> 1000 | E10: =C10*TAXA_MENSAL -> 99.656547 | F10: =C10+D10+E10 -> 13556.725 | G10: =F10*DY_MENSAL -> 94.897074 | H10: =H9+D10 -> 13000
A11: 9 | B11: =ROUNDUP(A11/12,0) -> 1 | C11: =F10 -> 13556.725 | D11: =APORTE -> 1000 | E11: =C11*TAXA_MENSAL -> 108.4538 | F11: =C11+D11+E11 -> 14665.179 | G11: =F11*DY_MENSAL -> 102.65625 | H11: =H10+D11 -> 14000
A12: 10 | B12: =ROUNDUP(A12/12,0) -> 1 | C12: =F11 -> 14665.179 | D12: =APORTE -> 1000 | E12: =C12*TAXA_MENSAL -> 117.32143 | F12: =C12+D12+E12 -> 15782.5 | G12: =F12*DY_MENSAL -> 110.4775 | H12: =H11+D12 -> 15000
A13: 11 | B13: =ROUNDUP(A13/12,0) -> 1 | C13: =F12 -> 15782.5 | D13: =APORTE -> 1000 | E13: =C13*TAXA_MENSAL -> 126.26 | F13: =C13+D13+E13 -> 16908.76 | G13: =F13*DY_MENSAL -> 118.36132 | H13: =H12+D13 -> 16000
A14: 12 | B14: =ROUNDUP(A14/12,0) -> 1 | C14: =F13 -> 16908.76 | D14: =APORTE -> 1000 | E14: =C14*TAXA_MENSAL -> 135.27008 | F14: =C14+D14+E14 -> 18044.03 | G14: =F14*DY_MENSAL -> 126.30821 | H14: =H13+D14 -> 17000
A15: 13 | B15: =ROUNDUP(A15/12,0) -> 2 | C15: =F14 -> 18044.03 | D15: =APORTE -> 1000 | E15: =C15*TAXA_MENSAL -> 144.35224 | F15: =C15+D15+E15 -> 19188.382 | G15: =F15*DY_MENSAL -> 134.31868 | H15: =H14+D15 -> 18000
... A362: 360 | B362: =ROUNDUP(A362/12,0) -> 30 | C362: =F361 -> 2146299.4 | D362: =APORTE -> 1000 | E362: =C362*TAXA_MENSAL -> 17170.395 | F362: =C362+D362+E362 -> 2164469.8 | G362: =F362*DY_MENSAL -> 15151.288 | H362: =H361+D362 -> 365000

Sheet BASE_FII
A1: BASE DE PARÂMETROS — PERFIS E TIPOS DE FII
A2: Matriz de distribuição percentual sugerida por perfil de investidor. Valores de referência para fins didáticos — cada linha soma 100%.
A3: MATRIZ DE ALOCAÇÃO POR PERFIL (% do aporte mensal)
A4: Perfil | B4: Papel | C4: Tijolo | D4: Híbridos | E4: FOFs | F4: Desenvolvimento | G4: Hotelaria | H4: Total
A5: Conservador | B5: 0.4 | C5: 0.25 | D5: 0.15 | E5: 0.1 | F5: 0.05 | G5: 0.05 | H5: =SUM(B5:G5) -> 1
A6: Moderado | B6: 0.25 | C6: 0.25 | D6: 0.2 | E6: 0.15 | F6: 0.1 | G6: 0.05 | H6: =SUM(B6:G6) -> 1
A7: Agressivo | B7: 0.15 | C7: 0.2 | D7: 0.15 | E7: 0.1 | F7: 0.25 | G7: 0.15 | H7: =SUM(B7:G7) -> 1
A9: Lista de perfis válidos (origem da validação em SIMULADOR!D13):
A11: TIPOS DE FII — DESCRIÇÃO CONCEITUAL
A12: Papel | B12: Fundos que investem em títulos de renda fixa imobiliária (CRI, LCI).
A13: Tijolo | B13: Fundos que investem diretamente em imóveis físicos (lajes, galpões, shoppings).
A14: Híbridos | B14: Combinam ativos de papel e de tijolo na mesma carteira.
A15: FOFs | B15: Fundo de Fundos: investem em cotas de outros FIIs.
A16: Desenvolvimento | B16: Fundos voltados à construção e incorporação de novos empreendimentos.
A17: Hotelaria | B17: Fundos especializados em empreendimentos hoteleiros.
